isthmuslib/__init__.py
isthmuslib/__main__.py
isthmuslib/cli.py
isthmuslib/config.py
isthmuslib/data_quality.py
isthmuslib/legacy.py
isthmuslib/logging.py
isthmuslib/plotting.py
isthmuslib/utils.py
isthmuslib/vectors.py
isthmuslib-0.0.113.dist-info/AUTHORS.rst
isthmuslib-0.0.113.dist-info/LICENSE
isthmuslib-0.0.113.dist-info/METADATA
isthmuslib-0.0.113.dist-info/WHEEL
isthmuslib-0.0.113.dist-info/entry_points.txt
isthmuslib-0.0.113.dist-info/top_level.txt
isthmuslib-0.0.113.dist-info/RECORD
