Metadata-Version: 2.1
Name: isthmuslib
Version: 0.0.113
Summary: Tooling for rapid data exploration, timeseries analysis, log extraction & visualization, etc
Home-page: https://github.com/mitchellpkt/python-isthmuslib
Author: Isthmus (Mitchell P. Krawiec-Thayer)
Author-email: isthmuslib@mitchellpkt.com
License: MIT
Project-URL: Changelog, https://github.com/mitchellpkt/python-isthmuslib/blob/master/CHANGELOG.rst
Project-URL: Issue Tracker, https://github.com/mitchellpkt/python-isthmuslib/issues
Classifier: Intended Audience :: Developers
Classifier: License :: OSI Approved :: MIT License
Classifier: Operating System :: Unix
Classifier: Operating System :: POSIX
Classifier: Operating System :: Microsoft :: Windows
Classifier: Operating System :: MacOS :: MacOS X
Classifier: Programming Language :: Python
Classifier: Programming Language :: Python :: 3.8
Classifier: Programming Language :: Python :: 3.9
Classifier: Programming Language :: Python :: 3.10
Classifier: Programming Language :: Python :: 3.11
Classifier: Programming Language :: Python :: Implementation :: CPython
Classifier: Programming Language :: Python :: Implementation :: PyPy
Classifier: Topic :: Utilities
Requires-Python: >=3.8
License-File: LICENSE
License-File: AUTHORS.rst
Requires-Dist: numpy
Requires-Dist: pandas
Requires-Dist: matplotlib
Requires-Dist: seaborn
Requires-Dist: loguru
Requires-Dist: pydantic
Requires-Dist: statsmodels
Requires-Dist: pytz
Requires-Dist: pyarrow
Requires-Dist: tqdm
